awsudo_py/__init__.py
awsudo_py/awsudo.py
awsudo_py-0.1.2.dist-info/entry_points.txt
awsudo_py-0.1.2.dist-info/LICENSE
awsudo_py-0.1.2.dist-info/WHEEL
awsudo_py-0.1.2.dist-info/METADATA
awsudo_py-0.1.2.dist-info/RECORD
